pommekit/__init__.py
pommekit/__main__.py
pommekit/_cli/__init__.py
pommekit/_cli/device_subcommand.py
pommekit/_cli/main_command.py
pommekit/_cli/user_subcommand.py
pommekit/_cli/util/__init__.py
pommekit/_cli/util/app_dirs.py
pommekit/_cli/util/device_utils.py
pommekit/_cli/util/rich_console.py
pommekit/_cli/util/selection.py
pommekit/_util/__init__.py
pommekit/_util/aio.py
pommekit/_util/crypto.py
pommekit/_util/event_listener.py
pommekit/_util/exponential_backoff.py
pommekit/_util/url.py
pommekit/albert/__init__.py
pommekit/albert/_activation.py
pommekit/albert/_device_csr.py
pommekit/albert/fairplay-chain.crt
pommekit/albert/fairplay.key
pommekit/anisette/__init__.py
pommekit/anisette/_types.py
pommekit/anisette/exceptions/__init__.py
pommekit/anisette/v3/__init__.py
pommekit/anisette/v3/_anisette_v3_provider.py
pommekit/apns/__init__.py
pommekit/apns/_client.py
pommekit/apns/_listener.py
pommekit/apns/_protocol/__init__.py
pommekit/apns/_protocol/commands.py
pommekit/apns/_protocol/packet.py
pommekit/apns/_protocol/topics.py
pommekit/apns/_protocol/transformers.py
pommekit/apns/_streams/__init__.py
pommekit/apns/_streams/apns_stream.py
pommekit/apns/_streams/client_stream.py
pommekit/apns/_streams/server.crt
pommekit/apns/_streams/server.key
pommekit/apns/_streams/server_stream.py
pommekit/apns/commands.py
pommekit/apns/types.py
pommekit/bags.py
pommekit/device/__init__.py
pommekit/device/_components.py
pommekit/device/_device.py
pommekit/device/_operating_system.py
pommekit/gsa/__init__.py
pommekit/gsa/_client.py
pommekit/gsa/_exceptions.py
pommekit/gsa/_srp.py
pommekit/gsa/params.pem
pommekit/ids/__init__.py
pommekit/ids/_user.py
pommekit/status_codes.py
pommekit-0.5.0.post1.dist-info/entry_points.txt
pommekit-0.5.0.post1.dist-info/LICENSE.md
pommekit-0.5.0.post1.dist-info/METADATA
pommekit-0.5.0.post1.dist-info/WHEEL
pommekit-0.5.0.post1.dist-info/RECORD
