Metadata-Version: 2.1
Name: pommekit
Version: 0.5.0.post1
Summary: Experimental Python package for various Apple APIs and services.
Home-page: https://github.com/Cypheriel/PommeKit
License: AGPL-3.0-or-later
Author: Mikel
Author-email: 61402923+Cypheriel@users.noreply.github.com
Requires-Python: >=3.11,<4.0
Classifier: License :: OSI Approved :: GNU Affero General Public License v3 or later (AGPLv3+)
Classifier: Programming Language :: Python :: 3
Classifier: Programming Language :: Python :: 3.11
Classifier: Programming Language :: Python :: 3.12
Requires-Dist: appdirs (>=1.4.4,<2.0.0)
Requires-Dist: cryptography (>=42.0.7,<43.0.0)
Requires-Dist: httpx (>=0.27.0,<0.28.0)
Requires-Dist: lxml (>=5.2.2,<6.0.0)
Requires-Dist: rich (>=13.7.1,<14.0.0)
Requires-Dist: typer (>=0.12.3,<0.13.0)
Requires-Dist: websockets (>=12.0,<13.0)
Project-URL: Bug Tracker, https://github.com/Cypheriel/PommeKit/issues
Project-URL: Repository, https://github.com/Cypheriel/PommeKit
